yav/__init__.py
yav/main.py
yav-1.0.1.dist-info/LICENSE
yav-1.0.1.dist-info/METADATA
yav-1.0.1.dist-info/WHEEL
yav-1.0.1.dist-info/entry_points.txt
yav-1.0.1.dist-info/top_level.txt
yav-1.0.1.dist-info/RECORD
