Metadata-Version: 2.1
Name: yav
Version: 1.0.1
Summary: yav- yet another venv management tool
Author: niuguy
Author-email: tf.wang.seu@gmail.com
License-File: LICENSE
